MANIFEST.in
setup.py
cpp/include/cert.hpp
cpp/include/certinfo.hpp
cpp/include/common.hpp
cpp/include/context.hpp
cpp/include/except.hpp
cpp/include/ext.hpp
cpp/include/hash.hpp
cpp/include/key.hpp
cpp/include/msg.hpp
cpp/include/rcobj.hpp
cpp/include/request.hpp
cpp/include/sign.hpp
cpp/src/cert.cpp
cpp/src/certinfo.cpp
cpp/src/common.cpp
cpp/src/context.cpp
cpp/src/except.cpp
cpp/src/ext.cpp
cpp/src/hash.cpp
cpp/src/key.cpp
cpp/src/msg.cpp
cpp/src/rcobj.cpp
cpp/src/request.cpp
cpp/src/sign.cpp
cprocsp/__init__.py
cprocsp/bytes.i
cprocsp/cert.i
cprocsp/certinfo.i
cprocsp/certutils.py
cprocsp/common.i
cprocsp/context.i
cprocsp/cryptoapi.py
cprocsp/csp.i
cprocsp/csp.py
cprocsp/csp_wrap_amd64.cxx
cprocsp/csp_wrap_ia32.cxx
cprocsp/decoder.py
cprocsp/defines.i
cprocsp/errors.i
cprocsp/ext.i
cprocsp/extra_defs.i
cprocsp/filetimes.py
cprocsp/functions.i
cprocsp/hash.i
cprocsp/key.i
cprocsp/msg.i
cprocsp/rdn.py
cprocsp/request.i
cprocsp/sign.i
cprocsp/wintypes.i
cryptoapy.egg-info/PKG-INFO
cryptoapy.egg-info/SOURCES.txt
cryptoapy.egg-info/dependency_links.txt
cryptoapy.egg-info/requires.txt
cryptoapy.egg-info/top_level.txt