Metadata-Version: 1.0
Name: cryptoapy
Version: 0.4.58
Summary: Python/C++ wrapper for Microsoft cryptoapi services (currently, Russian GOST algorithms only)
Home-page: UNKNOWN
Author: Andrew Rodionoff
Author-email: andviro@gmail.com
License: LGPL
Platform: Linux
Platform: Windows
